trame_server/LICENSE
trame_server/__init__.py
trame_server/client.py
trame_server/controller.py
trame_server/core.py
trame_server/http.py
trame_server/protocol.py
trame_server/state.py
trame_server/ui.py
trame_server/utils/__init__.py
trame_server/utils/argument_parser.py
trame_server/utils/asynchronous.py
trame_server/utils/banner.py
trame_server/utils/banner.txt
trame_server/utils/browser.py
trame_server/utils/desktop.py
trame_server/utils/hot_reload.py
trame_server/utils/logger.py
trame_server/utils/namespace.py
trame_server/utils/server.py
trame_server/utils/typed_state.py
trame_server/utils/version.py
trame_server-3.9.0.dist-info/licenses/LICENSE
trame_server-3.9.0.dist-info/METADATA
trame_server-3.9.0.dist-info/WHEEL
trame_server-3.9.0.dist-info/top_level.txt
trame_server-3.9.0.dist-info/RECORD
